televal/__init__.py
televal/evaluation/__init__.py
televal/evaluation/compute_metrics.py
televal/evaluation/compute_metrics_LLM.py
televal/evaluation/compute_scores.py
televal/evaluation/eval_prompt/__init__.py
televal/evaluation/eval_prompt/ac.py
televal/evaluation/eval_prompt/cs.py
televal/evaluation/eval_prompt/os.py
televal/evaluation/eval_prompt/qa.py
televal/generation/__init__.py
televal/generation/generator_api.py
televal/generation/generator_local.py
televal/generation/prompt_configs/CSQ.py
televal/generation/prompt_configs/MCQ.py
televal/generation/prompt_configs/QA.py
televal/generation/prompt_configs/SCQ.py
televal/generation/prompt_configs/TFQ.py
televal/generation/prompt_configs/__init__.py
televal/models/Baichuan.py
televal/models/GLM.py
televal/models/Gemma.py
televal/models/Jiutian.py
televal/models/Llama.py
televal/models/Minicpm.py
televal/models/Qwen.py
televal/models/Qwen3.py
televal/models/Telechat.py
televal/models/Yi.py
televal/models/__init__.py
televal/models/pangu.py
televal/models/test.py
televal/utils/__init__.py
televal/utils/data_helper.py
televal/visualization/__init__.py
televal/visualization/compute_ranking_average.py
televal/visualization/compute_ranking_single.py
televal-0.1.3.dist-info/METADATA
televal-0.1.3.dist-info/WHEEL
televal-0.1.3.dist-info/top_level.txt
televal-0.1.3.dist-info/RECORD
