Metadata-Version: 2.1
Name: televal
Version: 0.1.3
Summary: 一个面向运营商领域的人机测评工具，支持本地与API模型评估
Home-page: https://github.com/zsjslab/televal
Author: wang.yingying
Author-email: wang.yingying@ustcinfo.com
License: MIT
Classifier: Programming Language :: Python :: 3
Classifier: License :: OSI Approved :: MIT License
Classifier: Operating System :: OS Independent
Requires-Python: >=3.8
Requires-Dist: pandas
Requires-Dist: tqdm
Requires-Dist: openai
